LICENSE
MANIFEST.in
PKG-INFO
README.md
setup.py
safe_access/__init__.py
safe_access.egg-info/PKG-INFO
safe_access.egg-info/SOURCES.txt
safe_access.egg-info/dependency_links.txt
safe_access.egg-info/top_level.txt
safe_access.egg-info/zip-safe
tests/test.py