Metadata-Version: 1.1
Name: safe-access
Version: 1.1
Summary: Tool to make drilling into Python objects easy & painless
Home-page: https://github.com/jwegan/safe_access_py
Author: John Egan
Author-email: me@jwegan.com
License: MPL 2.0
Platform: UNKNOWN
Classifier: Development Status :: 3 - Alpha
Classifier: Intended Audience :: Developers
Classifier: License :: OSI Approved :: Mozilla Public License 2.0 (MPL 2.0)
Classifier: Topic :: Utilities
